tesstrain/__init__.py
tesstrain/__main__.py
tesstrain/arguments.py
tesstrain/generate.py
tesstrain/language_specific.py
tesstrain/py.typed
tesstrain/wrapper.py
tesstrain-0.2.0.dist-info/LICENSE
tesstrain-0.2.0.dist-info/METADATA
tesstrain-0.2.0.dist-info/WHEEL
tesstrain-0.2.0.dist-info/top_level.txt
tesstrain-0.2.0.dist-info/RECORD
