Metadata-Version: 2.2
Name: tesstrain
Version: 0.2.0
Summary: Training utils for Tesseract
Author: Tesseract contributors
License: Apache-2.0
Project-URL: Homepage, https://github.com/stefan6419846/tesstrain_package
Project-URL: Documentation, https://tesstrain.readthedocs.io/
Project-URL: Repository, https://github.com/stefan6419846/tesstrain_package
Project-URL: Issues, https://github.com/stefan6419846/tesstrain_package/issues
Project-URL: Changelog, https://github.com/stefan6419846/tesstrain_package/blob/main/CHANGELOG.md
Keywords: tesseract,tesseract-ocr,ocr,optical character recognition
Classifier: Development Status :: 5 - Production/Stable
Classifier: Intended Audience :: Developers
Classifier: Topic :: Scientific/Engineering :: Image Recognition
Classifier: License :: OSI Approved :: Apache Software License
Classifier: Programming Language :: Python :: 3
Classifier: Programming Language :: Python :: 3 :: Only
Classifier: Typing :: Typed
Requires-Python: <4,>=3.9
License-File: LICENSE
Requires-Dist: tqdm
Provides-Extra: dev
Requires-Dist: mypy; extra == "dev"
Requires-Dist: types-tqdm; extra == "dev"
Requires-Dist: codespell; extra == "dev"
Provides-Extra: docs
Requires-Dist: sphinx; extra == "docs"
Requires-Dist: furo; extra == "docs"
